{"101": {"ProductName": "Glue", "ManufacturingDate": "14-July-2021", "Quantity": 40, "Price": 20, "Status": "Available"}, "102": {"ProductName": "A4 Paper", "ManufacturingDate": "24-August-2021", "Quantity": 500, "Price": 5, "Status": "Available"}, "103": {"ProductName": "Pencil", "ManufacturingDate": "06-July-2021", "Quantity": 60, "Price": 5, "Status": "Available"}, "104": {"ProductName": "Eraser", "ManufacturingDate": "04-April-2021", "Quantity": 45, "Price": 10, "Status": "Available"}, "105": {"ProductName": "Stapler", "ManufacturingDate": "19-August-2021", "Quantity": 40, "Price": 40, "Status": "Available"}, "106": {"ProductName": "Paper Clip", "ManufacturingDate": "12-August-2021", "Quantity": 70, "Price": 10, "Status": "Available"}, "107": {"ProductName": "Highlighter", "ManufacturingDate": "03-August-2021", "Quantity": 55, "Price": 50, "Status": "Available"}, "108": {"ProductName": "Black Pen", "ManufacturingDate": "06-June-2021", "Quantity": 70, "Price": 10, "Status": "Available"}, "109": {"ProductName": "Blue Pen", "ManufacturingDate": "08-June-2021", "Quantity": 100, "Price": 10, "Status": "Available"}, "110": {"ProductName": "Red Pen", "ManufacturingDate": "31-August-2021", "Quantity": 60, "Price": 10, "Status": "Available"}, "111": {"ProductName": "Green Pen", "ManufacturingDate": "09-May-2021", "Quantity": 50, "Price": 10, "Status": "Available"}, "112": {"ProductName": "Scissor", "ManufacturingDate": "02-August-2021", "Quantity": 40, "Price": 30, "Status": "Available"}, "113": {"ProductName": "Small Notebook", "ManufacturingDate": "02-August-2021", "Quantity": 80, "Price": 35, "Status": "Available"}, "114": {"ProductName": "Calculator", "ManufacturingDate": "01-September-2021", "Quantity": 30, "Price": 100, "Status": "Available"}, "115": {"ProductName": "Tape", "ManufacturingDate": "14-March-2021", "Quantity": 65, "Price": 10, "Status": "Available"}, "116": {"ProductName": "Label", "ManufacturingDate": "16-August-2021", "Quantity": 30, "Price": 5, "Status": "Available"}, "117": {"ProductName": "Pencil Sharpener", "ManufacturingDate": "21-May-2021", "Quantity": 65, "Price": 5, "Status": "Available"}, "118": {"ProductName": "Envelope", "ManufacturingDate": "09-June-2021", "Quantity": 40, "Price": 2, "Status": "Available"}, "119": {"ProductName": "Blue Ink", "ManufacturingDate": "18-August-2021", "Quantity": 50, "Price": 30, "Status": "Available"}, "120": {"ProductName": "Black Ink", "ManufacturingDate": "25-July-2021", "Quantity": 50, "Price": 35, "Status": "Available"}, "121": {"ProductName": "Crayons", "ManufacturingDate": "13-June-2021", "Quantity": 55, "Price": 20, "Status": "Available"}, "122": {"ProductName": "Whitener Pen", "ManufacturingDate": "14-May-2021", "Quantity": 50, "Price": 30, "Status": "Available"}, "123": {"ProductName": "Marker", "ManufacturingDate": "01-March-2021", "Quantity": 37, "Price": 45, "Status": "Available"}, "124": {"ProductName": "File", "ManufacturingDate": "07-March-2021", "Quantity": 55, "Price": 40, "Status": "Available"}, "125": {"ProductName": "Scale Long", "ManufacturingDate": "19-June-2021", "Quantity": 60, "Price": 20, "Status": "Available"}, "126": {"ProductName": "Scale Small", "ManufacturingDate": "24-July-2021", "Quantity": 85, "Price": 15, "Status": "Available"}, "127": {"ProductName": "Long Notebook", "ManufacturingDate": "28-May-2021", "Quantity": 50, "Price": 60, "Status": "Available"}, "128": {"ProductName": "A4 Notebook", "ManufacturingDate": "12-June-2021", "Quantity": 100, "Price": 45, "Status": "Available"}, "129": {"ProductName": "White Chart", "ManufacturingDate": "23-June-2021", "Quantity": 110, "Price": 10, "Status": "Available"}, "130": {"ProductName": "Black Chart", "ManufacturingDate": "04-July-2021", "Quantity": 0, "Price": 10, "Status": "Not Available"}, "131": {"ProductName": "jashdhuhd", "ManufacturingDate": "jhddhuw", "Quantity": 153, "Price": 90, "Status": "a"}}